flask_admin_panel/__init__.py
flask_admin_panel/constant_config.py
flask_admin_panel/blueprints/__init__.py
flask_admin_panel/blueprints/admin_panel_blueprint.py
flask_admin_panel/controllers/__init__.py
flask_admin_panel/controllers/admin_panel_controller.py
flask_admin_panel/exceptions/__init__.py
flask_admin_panel/exceptions/exceptions_classes.py
flask_admin_panel/injectors/__init__.py
flask_admin_panel/injectors/admin_panel_injector.py
flask_admin_panel/interfaces/__init__.py
flask_admin_panel/interfaces/iadmin_panel_service.py
flask_admin_panel/middlewares/__init__.py
flask_admin_panel/middlewares/auth_middleware.py
flask_admin_panel/middlewares/auth_utils.py
flask_admin_panel/middlewares/base_response_handler.py
flask_admin_panel/repositories/__init__.py
flask_admin_panel/repositories/baserepository.py
flask_admin_panel/services/__init__.py
flask_admin_panel/services/admin_panel_service.py
flask_admin_panel/templates/flask_admin_panel/form.html
flask_admin_panel/templates/flask_admin_panel/index.html
flask_admin_panel/templates/flask_admin_panel/list.html
flask_admin_panel/templates/flask_admin_panel/login.html
flask_admin_panel/templates/flask_admin_panel/models_list.html
flask_admin_panel/tests/__init__.py
flask_admin_panel/tests/controllers/__init__.py
flask_admin_panel/tests/controllers/test_admin_panel_controllers.py
flask_admin_panel/tests/services/__init__.py
flask_admin_panel/tests/services/test_admin_panel_service.py
flask_admin_panel-0.1.0.dist-info/LICENSE
flask_admin_panel-0.1.0.dist-info/METADATA
flask_admin_panel-0.1.0.dist-info/WHEEL
flask_admin_panel-0.1.0.dist-info/top_level.txt
flask_admin_panel-0.1.0.dist-info/RECORD
