Metadata-Version: 2.1
Name: flask-admin-panel
Version: 0.1.0
Summary: Simple Admin Panel for Flask
Home-page: https://github.com/pranjgit/flask-admin-panel
Author: Pranjal Gharat
Author-email: pranjgit@gmail.com
License: UNKNOWN
Keywords: flask,flask-admin,admin-panel,flask-admin-panel,setuptools,development
Platform: UNKNOWN
Classifier: Development Status :: 3 - Alpha
Classifier: Intended Audience :: Developers
Classifier: Topic :: Software Development :: Build Tools
Classifier: License :: OSI Approved :: MIT License
Classifier: Programming Language :: Python :: 3.7
Classifier: Programming Language :: Python :: 3.8
Classifier: Programming Language :: Python :: 3.9
Classifier: Programming Language :: Python :: 3.10
Requires-Python: >=3.8, <4
Requires-Dist: Flask >=3.0.0
Requires-Dist: Flask-Injector >=0.15.0
Requires-Dist: Flask-JWT-Extended >=4.6.0
Requires-Dist: flask-marshmallow >=1.2.0
Requires-Dist: Flask-Migrate >=4.0.5
Requires-Dist: flask-restx >=1.3.0
Requires-Dist: Flask-SQLAlchemy >=3.1.1
Requires-Dist: Flask-WTF >=1.2.1
Requires-Dist: WTForms-Alchemy >=0.18.0
Provides-Extra: test
Requires-Dist: coverage ; extra == 'test'
Requires-Dist: pytest ; extra == 'test'
Requires-Dist: pytest-cov ; extra == 'test'
